pygsva/__init__.py
pygsva/config.py
pygsva/data_loader.py
pygsva/gsvap.py
pygsva/main.py
pygsva/param.py
pygsva/plage.py
pygsva/ssgsea.py
pygsva/utils.py
pygsva/zscore.py
pygsva/data/hsko.csv
pygsva/data/pbmc_exp.csv
pygsva-0.2.0.dist-info/licenses/LICENSE
pygsva-0.2.0.dist-info/METADATA
pygsva-0.2.0.dist-info/WHEEL
pygsva-0.2.0.dist-info/top_level.txt
pygsva-0.2.0.dist-info/RECORD
